{
    "key": "post_type_service",
    "title": "Services",
    "menu_order": 0,
    "active": true,
    "post_type": "service",
    "advanced_configuration": true,
    "import_source": "",
    "import_date": "",
    "labels": {
        "name": "Services",
        "singular_name": "Service",
        "menu_name": "Services",
        "all_items": "All Services",
        "edit_item": "Edit Service",
        "view_item": "View Service",
        "view_items": "View Services",
        "add_new_item": "Add New Service",
        "add_new": "Add New Service",
        "new_item": "New Service",
        "search_items": "Search Services",
        "not_found": "No services found",
        "not_found_in_trash": "No services found in Trash",
        "archives": "Service Archives",
        "item_published": "Service published.",
        "item_updated": "Service updated."
    },
    "description": "Pressure cleaning service pages — each entry renders through single-service.php.",
    "public": true,
    "hierarchical": false,
    "exclude_from_search": false,
    "publicly_queryable": true,
    "show_ui": true,
    "show_in_menu": true,
    "admin_menu_parent": "",
    "show_in_admin_bar": true,
    "show_in_nav_menus": true,
    "show_in_rest": true,
    "rest_base": "",
    "rest_namespace": "wp/v2",
    "rest_controller_class": "WP_REST_Posts_Controller",
    "menu_position": 21,
    "menu_icon": {
        "type": "dashicons",
        "value": "dashicons-water"
    },
    "rewrite": {
        "permalink_rewrite": "custom",
        "slug": "services",
        "with_front": false,
        "feeds": false,
        "pages": true
    },
    "query_var": "post_type_key",
    "query_var_name": "",
    "can_export": true,
    "delete_with_user": false,
    "capability_type": "post",
    "supports": [
        "title",
        "editor",
        "thumbnail",
        "excerpt",
        "page-attributes"
    ],
    "taxonomies": [],
    "has_archive": true,
    "has_archive_slug": "services",
    "enter_title_here": "Service name, eg Driveway Cleaning"
}
